multires/__init__.py
multires/euler.py
multires/hmra.py
multires/increase_resolution.py
multires/smra.py
multires-0.1.3.dist-info/LICENSE
multires-0.1.3.dist-info/METADATA
multires-0.1.3.dist-info/WHEEL
multires-0.1.3.dist-info/top_level.txt
multires-0.1.3.dist-info/RECORD
