Metadata-Version: 2.1
Name: multires
Version: 0.1.3
Summary: Implementation of the standard and hybrid multiresolution algorithm to generate first passage times and trajectories
Author-email: Juan Magalang <jarmsmagalang@gmail.com>
License-File: LICENSE
Requires-Dist: numpy
